ohana/__init__.py
ohana/config.py
ohana/models/__init__.py
ohana/models/unet_3d.py
ohana/predict/__init__.py
ohana/predict/base_predictor.py
ohana/predict/predict_cosmic_rays.py
ohana/predict/predict_rtn.py
ohana/predict/predict_snowball.py
ohana/predict/predictor.py
ohana/preprocessing/__init__.py
ohana/preprocessing/data_loader.py
ohana/preprocessing/preprocessor.py
ohana/preprocessing/reference_pixel_corrector.py
ohana/preprocessing/temporal_analyzer.py
ohana/tests/__init__.py
ohana/tests/test_training_set_creator.py
ohana/training/__init__.py
ohana/training/dataset.py
ohana/training/injections.py
ohana/training/training_set_creator.py
ohana/visualization/__init__.py
ohana/visualization/plotter.py
ohana-0.1.0.dist-info/licenses/LICENSE
ohana-0.1.0.dist-info/METADATA
ohana-0.1.0.dist-info/WHEEL
ohana-0.1.0.dist-info/entry_points.txt
ohana-0.1.0.dist-info/top_level.txt
ohana-0.1.0.dist-info/RECORD
