Metadata-Version: 2.4
Name: ohana
Version: 0.1.0
Summary: A deep learning-based tool for detecting and segmenting cosmic rays in astronomical images.
Home-page: https://github.com/bellalongo/ohana
Author: Bella Longo
Author-email: bellalongo.mail@gmail.com
Classifier: Programming Language :: Python :: 3
Classifier: License :: OSI Approved :: MIT License
Classifier: Operating System :: OS Independent
Requires-Python: >=3.8
License-File: LICENSE
Requires-Dist: torch==2.2.2
Requires-Dist: numpy==1.26.4
Requires-Dist: scipy==1.16.1
Requires-Dist: numba==0.61.2
Requires-Dist: scikit-image==0.25.2
Requires-Dist: pandas==2.3.1
Requires-Dist: h5py==3.14.0
Requires-Dist: PyYAML==6.0.2
Requires-Dist: astropy==7.1.0
Requires-Dist: tqdm==4.67.1
Dynamic: author
Dynamic: author-email
Dynamic: classifier
Dynamic: description
Dynamic: description-content-type
Dynamic: home-page
Dynamic: license-file
Dynamic: requires-dist
Dynamic: requires-python
Dynamic: summary
